gym_locm/__init__.py
gym_locm/agents.py
gym_locm/exceptions.py
gym_locm/util.py
gym_locm/engine/__init__.py
gym_locm/engine/action.py
gym_locm/engine/card.py
gym_locm/engine/card_generator.py
gym_locm/engine/enums.py
gym_locm/engine/game_state.py
gym_locm/engine/phases.py
gym_locm/engine/player.py
gym_locm/envs/__init__.py
gym_locm/envs/base_env.py
gym_locm/envs/battle.py
gym_locm/envs/constructed.py
gym_locm/envs/draft.py
gym_locm/envs/rewards.py
gym_locm/experiments/hyp-search.py
gym_locm/experiments/similarities.py
gym_locm/experiments/tournament.py
gym_locm/experiments/training.py
gym_locm/toolbox/consistency-checker.py
gym_locm/toolbox/predictor.py
gym_locm/toolbox/runner.py
gym_locm/toolbox/trainer_battle.py
gym_locm/toolbox/trainer_draft.py
gym_locm-2.0.0b1.dist-info/licenses/LICENSE
gym_locm-2.0.0b1.dist-info/METADATA
gym_locm-2.0.0b1.dist-info/WHEEL
gym_locm-2.0.0b1.dist-info/entry_points.txt
gym_locm-2.0.0b1.dist-info/top_level.txt
gym_locm-2.0.0b1.dist-info/RECORD
