Metadata-Version: 2.4
Name: gym-locm
Version: 2.0.0b1
Summary: Gymnasium environments for Legends of Code and Magic, a collectible card game designed for AI research
Author-email: Ronaldo e Silva Vieira <ronaldoesv@gmail.com>
License-Expression: MIT
Project-URL: repository, https://github.com/ronaldosvieira/gym-locm
Keywords: reinforcement-learning,collectible-card-games,gym-environment,legends-of-code-and-magic
Requires-Python: >=3.12
License-File: LICENSE
Requires-Dist: gymnasium>=1.2.3
Requires-Dist: numpy>=2.4.1
Dynamic: license-file
